BetFuryBotProject/__init__.py
BetFuryBotProject/bot_script.py
BetFuryBotProject/brw_run.py
BetFuryBotProject/create_wallets.py
BetFuryBotProject/excel.py
BetFuryBotProject/metamask.py
BetFuryBotProject/mnemonic_utils.py
BetFuryBotProject/test.py
BetFuryBotProject/tests.py
BetFuryBotProject-1.2.0.dist-info/LICENSE
BetFuryBotProject-1.2.0.dist-info/METADATA
BetFuryBotProject-1.2.0.dist-info/WHEEL
BetFuryBotProject-1.2.0.dist-info/top_level.txt
BetFuryBotProject-1.2.0.dist-info/RECORD
